espionage/__init__.py
espionage/constants.py
espionage/main.py
espionage/console/__init__.py
espionage/console/c_davailable.py
espionage/console/c_dbdata.py
espionage/console/c_main.py
espionage/console/input.py
espionage/modules/availability/__init__.py
espionage/modules/availability/domain_available.py
espionage/modules/osint/__init__.py
espionage/modules/osint/domain_available.py
espionage/modules/osint/domain_big_data.py
espionage/modules/parser/__init__.py
espionage/modules/parser/url_parser.py
espionage/modules/whois/__init__.py
espionage/modules/whois/domain_big_data.py
espionage-0.0.3.dist-info/LICENSE
espionage-0.0.3.dist-info/METADATA
espionage-0.0.3.dist-info/WHEEL
espionage-0.0.3.dist-info/entry_points.txt
espionage-0.0.3.dist-info/top_level.txt
espionage-0.0.3.dist-info/RECORD
