Metadata-Version: 2.1
Name: espionage
Version: 0.0.3
Summary: Espionage is open source intelligence gathering tool. This tool collect information related to domain. 
Home-page: https://github.com/iAbdullahMughal/espionage
Author: Muhammad Abdullah
Author-email: iamabdullahmughal@gmail.com
License: UNKNOWN
Project-URL: Bug Tracker, https://github.com/iAbdullahMughal/espionage/issues
Platform: UNKNOWN
Classifier: Programming Language :: Python :: 3.6
Classifier: License :: OSI Approved :: MIT License
Classifier: Operating System :: OS Independent
Requires-Python: >=3.6
License-File: LICENSE
Requires-Dist: requests (~=2.26.0)
Requires-Dist: beautifulsoup4 (~=4.10.0)
Requires-Dist: lxml
Requires-Dist: rich (~=10.16.1)
Requires-Dist: setuptools (~=57.0.0)
